Workbook

Sheet SuperMarket
A1: Invoice ID | B1: Branch | C1: City | D1: Customer type | E1: Gender | F1: Product line | G1: Unit price | H1: Quantity | I1: Tax 5% | J1: Sales | K1: Date | L1: Time | M1: Payment | N1: cogs | O1: gross margin percentage | P1: gross income | Q1: Rating | R1: DateTime | S1: Interarrival_Min | T1: IA_Clean
A2: 765-26-6951 | B2: Alex | C2: Yangon | D2: Member | E2: Female | F2: Sports and travel | G2: 72.61 | H2: 6 | I2: 21.783 | J2: 457.443 | K2: 43466 | L2: 0.44375 | M2: Credit card | N2: 435.66 | O2: 4.7619048 | P2: 21.783 | Q2: 6.9 | R2: =K2+L2 -> 43466.444 | S2: =IF(K2=K1, (R2-R1)*1440, "") | T2: =IF(S2="","",ROUND(S2,2))
A3: 651-88-7328 | B3: Alex | C3: Yangon | D3: Normal | E3: Female | F3: Fashion accessories | G3: 65.74 | H3: 9 | I3: 29.583 | J3: 621.243 | K3: 43466 | L3: 0.57986111 | M3: Cash | N3: 591.66 | O3: 4.7619048 | P3: 29.583 | Q3: 7.7 | R3: =K3+L3 -> 43466.58 | S3: =IF(K3=K2, (R3-R2)*1440, "") -> 196 | T3: =IF(S3="","",ROUND(S3,2)) -> 196
A4: 416-17-9926 | B4: Alex | C4: Yangon | D4: Member | E4: Female | F4: Electronic accessories | G4: 74.22 | H4: 10 | I4: 37.11 | J4: 779.31 | K4: 43466 | L4: 0.6125 | M4: Credit card | N4: 742.2 | O4: 4.7619048 | P4: 37.11 | Q4: 4.3 | R4: =K4+L4 -> 43466.613 | S4: =IF(K4=K3, (R4-R3)*1440, "") -> 47 | T4: =IF(S4="","",ROUND(S4,2)) -> 47
A5: 530-90-9855 | B5: Alex | C5: Yangon | D5: Member | E5: Male | F5: Home and lifestyle | G5: 47.59 | H5: 8 | I5: 19.036 | J5: 399.756 | K5: 43466 | L5: 0.61597222 | M5: Cash | N5: 380.72 | O5: 4.7619048 | P5: 19.036 | Q5: 5.7 | R5: =K5+L5 -> 43466.616 | S5: =IF(K5=K4, (R5-R4)*1440, "") -> 5 | T5: =IF(S5="","",ROUND(S5,2)) -> 5
A6: 182-52-7000 | B6: Alex | C6: Yangon | D6: Member | E6: Female | F6: Sports and travel | G6: 27.04 | H6: 4 | I6: 5.408 | J6: 113.568 | K6: 43466 | L6: 0.85138889 | M6: Ewallet | N6: 108.16 | O6: 4.7619048 | P6: 5.408 | Q6: 6.9 | R6: =K6+L6 -> 43466.851 | S6: =IF(K6=K5, (R6-R5)*1440, "") -> 339 | T6: =IF(S6="","",ROUND(S6,2)) -> 339
A7: 712-39-0363 | B7: Alex | C7: Yangon | D7: Member | E7: Male | F7: Food and beverages | G7: 41.66 | H7: 6 | I7: 12.498 | J7: 262.458 | K7: 43467 | L7: 0.64166667 | M7: Ewallet | N7: 249.96 | O7: 4.7619048 | P7: 12.498 | Q7: 5.6 | R7: =K7+L7 -> 43467.642 | S7: =IF(K7=K6, (R7-R6)*1440, "") | T7: =IF(S7="","",ROUND(S7,2))
A8: 504-35-8843 | B8: Alex | C8: Yangon | D8: Member | E8: Female | F8: Sports and travel | G8: 42.47 | H8: 1 | I8: 2.1235 | J8: 44.5935 | K8: 43467 | L8: 0.70625 | M8: Cash | N8: 42.47 | O8: 4.7619048 | P8: 2.1235 | Q8: 5.7 | R8: =K8+L8 -> 43467.706 | S8: =IF(K8=K7, (R8-R7)*1440, "") -> 93 | T8: =IF(S8="","",ROUND(S8,2)) -> 93
A9: 249-42-3782 | B9: Alex | C9: Yangon | D9: Normal | E9: Male | F9: Health and beauty | G9: 70.01 | H9: 5 | I9: 17.5025 | J9: 367.5525 | K9: 43468 | L9: 0.48333333 | M9: Ewallet | N9: 350.05 | O9: 4.7619048 | P9: 17.5025 | Q9: 5.5 | R9: =K9+L9 -> 43468.483 | S9: =IF(K9=K8, (R9-R8)*1440, "") | T9: =IF(S9="","",ROUND(S9,2))
A10: 749-24-1565 | B10: Alex | C10: Yangon | D10: Normal | E10: Female | F10: Health and beauty | G10: 23.03 | H10: 9 | I10: 10.3635 | J10: 217.6335 | K10: 43468 | L10: 0.50138889 | M10: Ewallet | N10: 207.27 | O10: 4.7619048 | P10: 10.3635 | Q10: 7.9 | R10: =K10+L10 -> 43468.501 | S10: =IF(K10=K9, (R10-R9)*1440, "") -> 26 | T10: =IF(S10="","",ROUND(S10,2)) -> 26
A11: 422-29-8786 | B11: Alex | C11: Yangon | D11: Normal | E11: Female | F11: Home and lifestyle | G11: 67.09 | H11: 5 | I11: 16.7725 | J11: 352.2225 | K11: 43468 | L11: 0.69930556 | M11: Credit card | N11: 335.45 | O11: 4.7619048 | P11: 16.7725 | Q11: 9.1 | R11: =K11+L11 -> 43468.699 | S11: =IF(K11=K10, (R11-R10)*1440, "") -> 285 | T11: =IF(S11="","",ROUND(S11,2)) -> 285
A12: 132-23-6451 | B12: Alex | C12: Yangon | D12: Member | E12: Male | F12: Health and beauty | G12: 20.97 | H12: 5 | I12: 5.2425 | J12: 110.0925 | K12: 43469 | L12: 0.55625 | M12: Cash | N12: 104.85 | O12: 4.7619048 | P12: 5.2425 | Q12: 7.8 | R12: =K12+L12 -> 43469.556 | S12: =IF(K12=K11, (R12-R11)*1440, "") | T12: =IF(S12="","",ROUND(S12,2))
A13: 731-14-2199 | B13: Alex | C13: Yangon | D13: Member | E13: Female | F13: Home and lifestyle | G13: 35.54 | H13: 10 | I13: 17.77 | J13: 373.17 | K13: 43469 | L13: 0.56527778 | M13: Ewallet | N13: 355.4 | O13: 4.7619048 | P13: 17.77 | Q13: 7 | R13: =K13+L13 -> 43469.565 | S13: =IF(K13=K12, (R13-R12)*1440, "") -> 13 | T13: =IF(S13="","",ROUND(S13,2)) -> 13
... A15: 489-82-1237 | B15: Alex | C15: Yangon | D15: Normal | E15: Female | F15: Electronic accessories | G15: 93.88 | H15: 7 | I15: 32.858 | J15: 690.018 | K15: 43470 | L15: 0.49375 | M15: Credit card | N15: 657.16 | O15: 4.7619048 | P15: 32.858 | Q15: 7.3 | R15: =K15+L15 -> 43470.494 | S15: =IF(K15=K14, (R15-R14)*1440, "") -> 26 | T15: =IF(S15="","",ROUND(S15,2)) -> 26
A16: 750-67-8428 | B16: Alex | C16: Yangon | D16: Member | E16: Female | F16: Health and beauty | G16: 74.69 | H16: 7 | I16: 26.1415 | J16: 548.9715 | K16: 43470 | L16: 0.54722222 | M16: Ewallet | N16: 522.83 | O16: 4.7619048 | P16: 26.1415 | Q16: 9.1 | R16: =K16+L16 -> 43470.547 | S16: ="" | T16: =IF(S16="","",ROUND(S16,2))
A17: 144-51-6085 | B17: Alex | C17: Yangon | D17: Member | E17: Male | F17: Home and lifestyle | G17: 70.74 | H17: 4 | I17: 14.148 | J17: 297.108 | K17: 43470 | L17: 0.67013889 | M17: Credit card | N17: 282.96 | O17: 4.7619048 | P17: 14.148 | Q17: 4.4 | R17: =K17+L17 -> 43470.67 | S17: =IF(K17=K16, (R17-R16)*1440, "") -> 177 | T17: =IF(S17="","",ROUND(S17,2)) -> 177
A18: 209-61-0206 | B18: Alex | C18: Yangon | D18: Normal | E18: Female | F18: Home and lifestyle | G18: 42.91 | H18: 5 | I18: 10.7275 | J18: 225.2775 | K18: 43470 | L18: 0.72847222 | M18: Ewallet | N18: 214.55 | O18: 4.7619048 | P18: 10.7275 | Q18: 6.1 | R18: =K18+L18 -> 43470.728 | S18: =IF(K18=K17, (R18-R17)*1440, "") -> 84 | T18: =IF(S18="","",ROUND(S18,2)) -> 84
A19: 490-29-1201 | B19: Alex | C19: Yangon | D19: Normal | E19: Female | F19: Sports and travel | G19: 15.34 | H19: 1 | I19: 0.767 | J19: 16.107 | K19: 43471 | L19: 0.46458333 | M19: Cash | N19: 15.34 | O19: 4.7619048 | P19: 0.767 | Q19: 6.5 | R19: =K19+L19 -> 43471.465 | S19: =IF(K19=K18, (R19-R18)*1440, "") | T19: =IF(S19="","",ROUND(S19,2))
A20: 704-11-6354 | B20: Alex | C20: Yangon | D20: Member | E20: Male | F20: Home and lifestyle | G20: 58.9 | H20: 8 | I20: 23.56 | J20: 494.76 | K20: 43471 | L20: 0.47430556 | M20: Cash | N20: 471.2 | O20: 4.7619048 | P20: 23.56 | Q20: 8.9 | R20: =K20+L20 -> 43471.474 | S20: =IF(K20=K19, (R20-R19)*1440, "") -> 14 | T20: =IF(S20="","",ROUND(S20,2)) -> 14
A21: 846-10-0341 | B21: Alex | C21: Yangon | D21: Normal | E21: Female | F21: Fashion accessories | G21: 42.57 | H21: 7 | I21: 14.8995 | J21: 312.8895 | K21: 43471 | L21: 0.49375 | M21: Cash | N21: 297.99 | O21: 4.7619048 | P21: 14.8995 | Q21: 6.8 | R21: =K21+L21 -> 43471.494 | S21: =IF(K21=K20, (R21-R20)*1440, "") -> 28 | T21: =IF(S21="","",ROUND(S21,2)) -> 28
A22: 852-82-2749 | B22: Alex | C22: Yangon | D22: Normal | E22: Male | F22: Sports and travel | G22: 64.59 | H22: 4 | I22: 12.918 | J22: 271.278 | K22: 43471 | L22: 0.56597222 | M22: Ewallet | N22: 258.36 | O22: 4.7619048 | P22: 12.918 | Q22: 9.3 | R22: =K22+L22 -> 43471.566 | S22: =IF(K22=K21, (R22-R21)*1440, "") -> 104 | T22: =IF(S22="","",ROUND(S22,2)) -> 104
A23: 662-72-2873 | B23: Alex | C23: Yangon | D23: Normal | E23: Female | F23: Food and beverages | G23: 40.94 | H23: 5 | I23: 10.235 | J23: 214.935 | K23: 43471 | L23: 0.58194444 | M23: Ewallet | N23: 204.7 | O23: 4.7619048 | P23: 10.235 | Q23: 9.9 | R23: =K23+L23 -> 43471.582 | S23: =IF(K23=K22, (R23-R22)*1440, "") -> 23 | T23: =IF(S23="","",ROUND(S23,2)) -> 23
A24: 126-54-1082 | B24: Alex | C24: Yangon | D24: Member | E24: Female | F24: Home and lifestyle | G24: 21.54 | H24: 9 | I24: 9.693 | J24: 203.553 | K24: 43472 | L24: 0.48888889 | M24: Credit card | N24: 193.86 | O24: 4.7619048 | P24: 9.693 | Q24: 8.8 | R24: =K24+L24 -> 43472.489 | S24: =IF(K24=K23, (R24-R23)*1440, "") | T24: =IF(S24="","",ROUND(S24,2))
A25: 541-48-8554 | B25: Alex | C25: Yangon | D25: Normal | E25: Male | F25: Sports and travel | G25: 60.95 | H25: 9 | I25: 27.4275 | J25: 575.9775 | K25: 43472 | L25: 0.50555556 | M25: Credit card | N25: 548.55 | O25: 4.7619048 | P25: 27.4275 | Q25: 6 | R25: =K25+L25 -> 43472.506 | S25: =IF(K25=K24, (R25-R24)*1440, "") -> 24 | T25: =IF(S25="","",ROUND(S25,2)) -> 24
A26: 799-71-1548 | B26: Alex | C26: Yangon | D26: Member | E26: Male | F26: Electronic accessories | G26: 77.72 | H26: 4 | I26: 15.544 | J26: 326.424 | K26: 43472 | L26: 0.67430556 | M26: Credit card | N26: 310.88 | O26: 4.7619048 | P26: 15.544 | Q26: 8.8 | R26: =K26+L26 -> 43472.674 | S26: =IF(K26=K25, (R26-R25)*1440, "") -> 243 | T26: =IF(S26="","",ROUND(S26,2)) -> 243
A27: 674-15-9296 | B27: Alex | C27: Yangon | D27: Normal | E27: Male | F27: Sports and travel | G27: 37.14 | H27: 5 | I27: 9.285 | J27: 194.985 | K27: 43473 | L27: 0.54513889 | M27: Ewallet | N27: 185.7 | O27: 4.7619048 | P27: 9.285 | Q27: 5 | R27: =K27+L27 -> 43473.545 | S27: =IF(K27=K26, (R27-R26)*1440, "") | T27: =IF(S27="","",ROUND(S27,2))
A28: 124-31-1458 | B28: Alex | C28: Yangon | D28: Member | E28: Female | F28: Electronic accessories | G28: 79.59 | H28: 3 | I28: 11.9385 | J28: 250.7085 | K28: 43473 | L28: 0.60416667 | M28: Cash | N28: 238.77 | O28: 4.7619048 | P28: 11.9385 | Q28: 6.6 | R28: =K28+L28 -> 43473.604 | S28: =IF(K28=K27, (R28-R27)*1440, "") -> 85 | T28: =IF(S28="","",ROUND(S28,2)) -> 85
... A1001: 364-34-2972 | B1001: Giza | C1001: Naypyitaw | D1001: Member | E1001: Male | F1001: Electronic accessories | G1001: 96.82 | H1001: 3 | I1001: 14.523 | J1001: 304.983 | K1001: 43554 | L1001: 0.85902778 | M1001: Cash | N1001: 290.46 | O1001: 4.7619048 | P1001: 14.523 | Q1001: 6.7 | R1001: =K1001+L1001 -> 43554.859 | S1001: =IF(K1001=K1000, (R1001-R1000)*1440, "") -> 71 | T1001: =IF(S1001="","",ROUND(S1001,2)) -> 71
R1006: ortalama | S1006: =AVERAGE(T:T) -> 119.67255
R1007: standart sapma | S1007: =_xlfn.STDEV.S(T:T) -> 111.5205

Sheet Histogram Analizi
A1: Bin | B1: Frekans | C1: Kümülatif %
A2: 0 | B2: 1 | C2: 0.0013586957
A3: 0.54589844 | B3: 0 | C3: 0.0013586957
A4: 1.0917969 | B4: 5 | C4: 0.0081521739
A5: 1.6376953 | B5: 0 | C5: 0.0081521739
A6: 2.1835938 | B6: 3 | C6: 0.012228261
A7: 2.7294922 | B7: 0 | C7: 0.012228261
A8: 3.2753906 | B8: 9 | C8: 0.024456522
A9: 3.8212891 | B9: 0 | C9: 0.024456522
A10: 4.3671875 | B10: 5 | C10: 0.03125
A11: 4.9130859 | B11: 0 | C11: 0.03125
A12: 5.4589844 | B12: 4 | C12: 0.036684783
A13: 6.0048828 | B13: 6 | C13: 0.044836957
... A1025: 558.4541 | B1025: 0 | C1025: 0.9986413
A1026: Diğer | B1026: 1 | C1026: 1

Sheet Histogram
A1: 196 | C1: 0 | I1: Bin | J1: Frekans | K1: Alt (a) | L1: Üst (b) | M1: Oi (Gözlenen) | N1: Pi (Olasılık) | O1: Ei (Beklenen) | P1: (Oi−Ei)^2/Ei | R1: n
A2: 47 | C2: 30 | I2: 0 | J2: 1 | K2: 0 | L2: =I3 -> 30 | M2: =J2+J3 -> 174 | N2: =EXP(-$E$8*K2)-EXP(-$E$8*L2) -> 0.22173177 | O2: =$R$2*N2 -> 163.19458 | P2: =IF(O2<5,"",(M2-O2)^2/O2) -> 0.71544685 | R2: =SUM(M:M) -> 736
A3: 5 | C3: 60 | E3: Ortalama | G3: standart sapma | I3: 30 | J3: 173 | K3: =L2 -> 30 | L3: =I4 -> 60 | M3: =J4 -> 121 | N3: =EXP(-$E$8*K3)-EXP(-$E$8*L3) -> 0.17256679 | O3: =$R$2*N3 -> 127.00916 | P3: =IF(O3<5,"",(M3-O3)^2/O3) -> 0.28431013
A4: 339 | C4: 90 | E4: =AVERAGE(A:A) -> 119.67255 | G4: =_xlfn.STDEV.S(A:A) -> 111.5205 | I4: 60 | J4: 121 | K4: =L3 -> 60 | L4: =I5 -> 90 | M4: =J5 -> 96 | N4: =EXP(-$E$8*K4)-EXP(-$E$8*L4) -> 0.13430325 | O4: =$R$2*N4 -> 98.847193 | P4: =IF(O4<5,"",(M4-O4)^2/O4) -> 0.08201052 | R4: Ki-kare (χ²)
A5: 93 | C5: 120 | I5: 90 | J5: 96 | K5: =L4 -> 90 | L5: =I6 -> 120 | M5: =J6 -> 62 | N5: =EXP(-$E$8*K5)-EXP(-$E$8*L5) -> 0.10452395 | O5: =$R$2*N5 -> 76.92963 | P5: =IF(O5<5,"",(M5-O5)^2/O5) -> 2.8973733 | R5: =SUM(P:P) -> 12.683076
A6: 26 | C6: 150 | I6: 120 | J6: 62 | K6: =L5 -> 120 | L6: =I7 -> 150 | M6: =J7 -> 59 | N6: =EXP(-$E$8*K6)-EXP(-$E$8*L6) -> 0.081347673 | O6: =$R$2*N6 -> 59.871887 | P6: =IF(O6<5,"",(M6-O6)^2/O6) -> 0.012696898 | R6: k
A7: 285 | C7: 180 | E7: Lambda | I7: 150 | J7: 59 | K7: =L6 -> 150 | L7: =I8 -> 180 | M7: =J8 -> 54 | N7: =EXP(-$E$8*K7)-EXP(-$E$8*L7) -> 0.063310309 | O7: =$R$2*N7 -> 46.596388 | P7: =IF(O7<5,"",(M7-O7)^2/O7) -> 1.176346 | R7: =COUNTIF(P:P,">0") -> 14
A8: 13 | C8: 210 | E8: =1/E4 -> 0.0083561348 | I8: 180 | J8: 54 | K8: =L7 -> 180 | L8: =I9 -> 210 | M8: =J9 -> 35 | N8: =EXP(-$E$8*K8)-EXP(-$E$8*L8) -> 0.049272402 | O8: =$R$2*N8 -> 36.264488 | P8: =IF(O8<5,"",(M8-O8)^2/O8) -> 0.044090803 | R8: df
A9: 26 | C9: 240 | I9: 210 | J9: 35 | K9: =L8 -> 210 | L9: =I10 -> 240 | M9: =J10 -> 24 | N9: =EXP(-$E$8*K9)-EXP(-$E$8*L9) -> 0.038347145 | O9: =$R$2*N9 -> 28.223499 | P9: =IF(O9<5,"",(M9-O9)^2/O9) -> 0.63202455 | R9: =R7-2 -> 12
A10: 177 | C10: 270 | I10: 240 | J10: 24 | K10: =L9 -> 240 | L10: =I11 -> 270 | M10: =J11 -> 26 | N10: =EXP(-$E$8*K10)-EXP(-$E$8*L10) -> 0.029844365 | O10: =$R$2*N10 -> 21.965453 | P10: =IF(O10<5,"",(M10-O10)^2/O10) -> 0.74105335 | R10: Kritik χ² (0,05)
A11: 84 | C11: 300 | I11: 270 | J11: 26 | K11: =L10 -> 270 | L11: =I12 -> 300 | M11: =J12 -> 24 | N11: =EXP(-$E$8*K11)-EXP(-$E$8*L11) -> 0.023226921 | O11: =$R$2*N11 -> 17.095014 | P11: =IF(O11<5,"",(M11-O11)^2/O11) -> 2.789049 | R11: =_xlfn.CHISQ.INV.RT(0.05,R9) -> 21.02607
A12: 14 | C12: 330 | I12: 300 | J12: 24 | K12: =L11 -> 300 | L12: =I13 -> 330 | M12: =J13 -> 13 | N12: =EXP(-$E$8*K12)-EXP(-$E$8*L12) -> 0.018076775 | O12: =$R$2*N12 -> 13.304506 | P12: =IF(O12<5,"",(M12-O12)^2/O12) -> 0.0069693735 | R12: Karar
A13: 28 | C13: 360 | I13: 330 | J13: 13 | K13: =L12 -> 330 | L13: =I14 -> 360 | M13: =J14 -> 16 | N13: =EXP(-$E$8*K13)-EXP(-$E$8*L13) -> 0.01406858 | O13: =$R$2*N13 -> 10.354475 | P13: =IF(O13<5,"",(M13-O13)^2/O13) -> 3.0780855 | R13: =IF(R5<=R11,"KABUL","RED") -> KABUL
A14: 104 | C14: 390 | I14: 360 | J14: 16 | K14: =L13 -> 360 | L14: =I15 -> 390 | M14: =J15 -> 7 | N14: =EXP(-$E$8*K14)-EXP(-$E$8*L14) -> 0.010949129 | O14: =$R$2*N14 -> 8.0585586 | P14: =IF(O14<5,"",(M14-O14)^2/O14) -> 0.13905046
A15: 23 | C15: 420 | I15: 390 | J15: 7 | K15: =L14 -> 390 | L15: =I16 -> 420 | M15: =J16 -> 7 | N15: =EXP(-$E$8*K15)-EXP(-$E$8*L15) -> 0.0085213589 | O15: =$R$2*N15 -> 6.2717201 | P15: =IF(O15<5,"",(M15-O15)^2/O15) -> 0.084568755
A16: 24 | C16: 450 | I16: 420 | J16: 7 | K16: =L15 -> 420 | L16: =I17 -> 450 | M16: =J17 -> 3 | N16: =EXP(-$E$8*K16)-EXP(-$E$8*L16) -> 0.0066319029 | O16: =$R$2*N16 -> 4.8810805 | P16: =IF(O16<5,"",(M16-O16)^2/O16)
A17: 243 | C17: 480 | I17: 450 | J17: 3 | K17: =L16 -> 450 | L17: =I18 -> 480 | M17: =J18 -> 8 | N17: =EXP(-$E$8*K17)-EXP(-$E$8*L17) -> 0.0051613993 | O17: =$R$2*N17 -> 3.7987899 | P17: =IF(O17<5,"",(M17-O17)^2/O17)
A18: 85 | C18: 510 | I18: 480 | J18: 8 | K18: =L17 -> 480 | L18: =I19 -> 510 | M18: =J19 -> 5 | N18: =EXP(-$E$8*K18)-EXP(-$E$8*L18) -> 0.0040169531 | O18: =$R$2*N18 -> 2.9564775 | P18: =IF(O18<5,"",(M18-O18)^2/O18)
A19: 162 | C19: 540 | I19: 510 | J19: 5 | K19: =L18 -> 510 | L19: =I20 -> 540 | M19: =J20 -> 1 | N19: =EXP(-$E$8*K19)-EXP(-$E$8*L19) -> 0.003126267 | O19: =$R$2*N19 -> 2.3009325 | P19: =IF(O19<5,"",(M19-O19)^2/O19)
A20: 54 | I20: 540 | J20: 1 | K20: =L19 -> 540 | L20: =I21 -> Diğer | M20: =J21 -> 1
A21: 146 | I21: Diğer | J21: 1
A22: 33
A23: 43
A24: 32
A25: 125
A26: 172
A27: 138
A28: 58
A29: 35
A30: 172
A31: 299
A32: 80
A33: 398
... A736: 71

Sheet RNG
A1: a | B1: 12
A2: c | B2: 19
A3: m | B3: 50
A4: X0 (seed) | B4: 7
A6: i | B6: Xi | C6: Ui = Xi/m | E6: U (sorted) | F6: i | G6: D+ = i/n - Ui | H6: D- | I6: n | J6: D | L6: Dmax
A7: 0 | B7: =$B$4 -> 7 | C7: =B7/$B$3 -> 0.14 | E7: =SMALL($C$7:$C$56,ROW(A1)) -> 0.06 | F7: 1 | G7: =F7/$I$7 - E7 -> -0.04 | H7: =E7 - (F7-1)/$I$7 -> 0.06 | I7: 50 | J7: =MAX(G7:H7) -> 0.06 | L7: =MAX(J7:J56) -> 0.06
A8: =A7+1 -> 1 | B8: =MOD($B$1*B7+$B$2,$B$3) -> 3 | C8: =B8/$B$3 -> 0.06 | E8: =SMALL($C$7:$C$56,ROW(A2)) -> 0.06 | F8: =F7+1 -> 2 | G8: =F8/$I$7 - E8 -> -0.02 | H8: =E8 - (F8-1)/$I$7 -> 0.04 | J8: =MAX(G8:H8) -> 0.04 | L8: Dkritik (0.05)
A9: =A8+1 -> 2 | B9: =MOD($B$1*B8+$B$2,$B$3) -> 5 | C9: =B9/$B$3 -> 0.1 | E9: =SMALL($C$7:$C$56,ROW(A3)) -> 0.06 | F9: =F8+1 -> 3 | G9: =F9/$I$7 - E9 -> 0 | H9: =E9 - (F9-1)/$I$7 -> 0.02 | J9: =MAX(G9:H9) -> 0.02 | L9: =1.36/SQRT($I$7) -> 0.19233304
A10: =A9+1 -> 3 | B10: =MOD($B$1*B9+$B$2,$B$3) -> 29 | C10: =B10/$B$3 -> 0.58 | E10: =SMALL($C$7:$C$56,ROW(A4)) -> 0.1 | F10: =F9+1 -> 4 | G10: =F10/$I$7 - E10 -> -0.02 | H10: =E10 - (F10-1)/$I$7 -> 0.04 | J10: =MAX(G10:H10) -> 0.04 | L10: Karar
A11: =A10+1 -> 4 | B11: =MOD($B$1*B10+$B$2,$B$3) -> 17 | C11: =B11/$B$3 -> 0.34 | E11: =SMALL($C$7:$C$56,ROW(A5)) -> 0.1 | F11: =F10+1 -> 5 | G11: =F11/$I$7 - E11 -> 0 | H11: =E11 - (F11-1)/$I$7 -> 0.02 | J11: =MAX(G11:H11) -> 0.02 | L11: =IF(L7<=L9,"KABUL (Uniform)","RED (Uniform değil)") -> KABUL (Uniform)
A12: =A11+1 -> 5 | B12: =MOD($B$1*B11+$B$2,$B$3) -> 23 | C12: =B12/$B$3 -> 0.46 | E12: =SMALL($C$7:$C$56,ROW(A6)) -> 0.1 | F12: =F11+1 -> 6 | G12: =F12/$I$7 - E12 -> 0.02 | H12: =E12 - (F12-1)/$I$7 -> 0 | J12: =MAX(G12:H12) -> 0.02
A13: =A12+1 -> 6 | B13: =MOD($B$1*B12+$B$2,$B$3) -> 45 | C13: =B13/$B$3 -> 0.9 | E13: =SMALL($C$7:$C$56,ROW(A7)) -> 0.14 | F13: =F12+1 -> 7 | G13: =F13/$I$7 - E13 -> 0 | H13: =E13 - (F13-1)/$I$7 -> 0.02 | J13: =MAX(G13:H13) -> 0.02
A14: =A13+1 -> 7 | B14: =MOD($B$1*B13+$B$2,$B$3) -> 9 | C14: =B14/$B$3 -> 0.18 | E14: =SMALL($C$7:$C$56,ROW(A8)) -> 0.14 | F14: =F13+1 -> 8 | G14: =F14/$I$7 - E14 -> 0.02 | H14: =E14 - (F14-1)/$I$7 -> 0 | J14: =MAX(G14:H14) -> 0.02
A15: =A14+1 -> 8 | B15: =MOD($B$1*B14+$B$2,$B$3) -> 27 | C15: =B15/$B$3 -> 0.54 | E15: =SMALL($C$7:$C$56,ROW(A9)) -> 0.14 | F15: =F14+1 -> 9 | G15: =F15/$I$7 - E15 -> 0.04 | H15: =E15 - (F15-1)/$I$7 -> -0.02 | J15: =MAX(G15:H15) -> 0.04
A16: =A15+1 -> 9 | B16: =MOD($B$1*B15+$B$2,$B$3) -> 43 | C16: =B16/$B$3 -> 0.86 | E16: =SMALL($C$7:$C$56,ROW(A10)) -> 0.18 | F16: =F15+1 -> 10 | G16: =F16/$I$7 - E16 -> 0.02 | H16: =E16 - (F16-1)/$I$7 -> 0 | J16: =MAX(G16:H16) -> 0.02
A17: =A16+1 -> 10 | B17: =MOD($B$1*B16+$B$2,$B$3) -> 35 | C17: =B17/$B$3 -> 0.7 | E17: =SMALL($C$7:$C$56,ROW(A11)) -> 0.18 | F17: =F16+1 -> 11 | G17: =F17/$I$7 - E17 -> 0.04 | H17: =E17 - (F17-1)/$I$7 -> -0.02 | J17: =MAX(G17:H17) -> 0.04
A18: =A17+1 -> 11 | B18: =MOD($B$1*B17+$B$2,$B$3) -> 39 | C18: =B18/$B$3 -> 0.78 | E18: =SMALL($C$7:$C$56,ROW(A12)) -> 0.18 | F18: =F17+1 -> 12 | G18: =F18/$I$7 - E18 -> 0.06 | H18: =E18 - (F18-1)/$I$7 -> -0.04 | J18: =MAX(G18:H18) -> 0.06
A19: =A18+1 -> 12 | B19: =MOD($B$1*B18+$B$2,$B$3) -> 37 | C19: =B19/$B$3 -> 0.74 | E19: =SMALL($C$7:$C$56,ROW(A13)) -> 0.26 | F19: =F18+1 -> 13 | G19: =F19/$I$7 - E19 -> 0 | H19: =E19 - (F19-1)/$I$7 -> 0.02 | J19: =MAX(G19:H19) -> 0.02
A20: =A19+1 -> 13 | B20: =MOD($B$1*B19+$B$2,$B$3) -> 13 | C20: =B20/$B$3 -> 0.26 | E20: =SMALL($C$7:$C$56,ROW(A14)) -> 0.26 | F20: =F19+1 -> 14 | G20: =F20/$I$7 - E20 -> 0.02 | H20: =E20 - (F20-1)/$I$7 -> 0 | J20: =MAX(G20:H20) -> 0.02
A21: =A20+1 -> 14 | B21: =MOD($B$1*B20+$B$2,$B$3) -> 25 | C21: =B21/$B$3 -> 0.5 | E21: =SMALL($C$7:$C$56,ROW(A15)) -> 0.3 | F21: =F20+1 -> 15 | G21: =F21/$I$7 - E21 -> 0 | H21: =E21 - (F21-1)/$I$7 -> 0.02 | J21: =MAX(G21:H21) -> 0.02
A22: =A21+1 -> 15 | B22: =MOD($B$1*B21+$B$2,$B$3) -> 19 | C22: =B22/$B$3 -> 0.38 | E22: =SMALL($C$7:$C$56,ROW(A16)) -> 0.3 | F22: =F21+1 -> 16 | G22: =F22/$I$7 - E22 -> 0.02 | H22: =E22 - (F22-1)/$I$7 -> 0 | J22: =MAX(G22:H22) -> 0.02
A23: =A22+1 -> 16 | B23: =MOD($B$1*B22+$B$2,$B$3) -> 47 | C23: =B23/$B$3 -> 0.94 | E23: =SMALL($C$7:$C$56,ROW(A17)) -> 0.34 | F23: =F22+1 -> 17 | G23: =F23/$I$7 - E23 -> 0 | H23: =E23 - (F23-1)/$I$7 -> 0.02 | J23: =MAX(G23:H23) -> 0.02
... A56: =A55+1 -> 49 | B56: =MOD($B$1*B55+$B$2,$B$3) -> 43 | C56: =B56/$B$3 -> 0.86 | E56: =SMALL($C$7:$C$56,ROW(A50)) -> 0.98 | F56: =F55+1 -> 50 | G56: =F56/$I$7 - E56 -> 0.02 | H56: =E56 - (F56-1)/$I$7 -> 0 | J56: =MAX(G56:H56) -> 0.02

Sheet Simulasyon
A1: Lambda (geliş) | B1: =Histogram!E8 -> 0.0083561348 | L1: n | M1: 25
A2: Mu (hizmet) | B2: 0.012 | L2: Ortalama Bekleme (Wq) | M2: =AVERAGE(I7:I31) -> 62.349761
L3: Ortalama Sistem Süresi (W) | M3: =AVERAGE(J7:J31) -> 142.34489
L4: Ortalama Servis Süresi | M4: =AVERAGE(F7:F31) -> 79.995128
A5: i | B5: U_arr | C5: Interarrival (dk) | D5: Arrival time | E5: U_srv | F5: Service time (dk) | G5: Service start | H5: Service end | I5: Waiting (dk) | J5: System time (dk) | L5: Kullanım oranı (ρ = λ/μ) | M5: =$B$1/$B$2 -> 0.69634457
A6: müşteri no | B6: geliş için uniform | C6: −ln(U)/λ | D6: geliş zamanı (kümülatif) | E6: hizmet için uniform | F6: −ln(U)/μ | G6: hizmet başlama zamanı | H6: bitiş zamanı | I6: kuyruk bekleme | J6: sistemde kalma | L6: Ortalama Kuyruk Uzunluğu (Lq) | M6: =$B$1*M2 -> 0.52100301
A7: 1 | B7: {=INDEX(RNG!$C$7:$C$106, (A7-1)*2+1)} -> 0.14 | C7: =-LN(B7)/$B$1 -> 235.28975 | D7: =C7 -> 235.28975 | E7: {=INDEX(RNG!$C$7:$C$106, (A7-1)*2+2)} -> 0.06 | F7: =-LN(E7)/$B$2 -> 234.45089 | G7: =D7 -> 235.28975 | H7: =G7 + F7 -> 469.74064 | I7: =G7 - D7 -> 0 | J7: =H7 - D7 -> 234.45089 | L7: Ortalama Sistem Müşteri Sayısı (L) (L≈λ⋅W) | M7: =$B$1*M3 -> 1.1894531
A8: 2 | B8: {=INDEX(RNG!$C$7:$C$106, (A8-1)*2+1)} -> 0.1 | C8: =-LN(B8)/$B$1 -> 275.55624 | D8: =D7 + C8 -> 510.84599 | E8: {=INDEX(RNG!$C$7:$C$106, (A8-1)*2+2)} -> 0.58 | F8: =-LN(E8)/$B$2 -> 45.393931 | G8: =MAX(D8,H7) -> 510.84599 | H8: =G8 + F8 -> 556.23992 | I8: =G8 - D8 -> 0 | J8: =H8 - D8 -> 45.393931
A9: 3 | B9: {=INDEX(RNG!$C$7:$C$106, (A9-1)*2+1)} -> 0.34 | C9: =-LN(B9)/$B$1 -> 129.10391 | D9: =D8 + C9 -> 639.9499 | E9: {=INDEX(RNG!$C$7:$C$106, (A9-1)*2+2)} -> 0.46 | F9: =-LN(E9)/$B$2 -> 64.710732 | G9: =MAX(D9,H8) -> 639.9499 | H9: =G9 + F9 -> 704.66063 | I9: =G9 - D9 -> 0 | J9: =H9 - D9 -> 64.710732
A10: 4 | B10: {=INDEX(RNG!$C$7:$C$106, (A10-1)*2+1)} -> 0.9 | C10: =-LN(B10)/$B$1 -> 12.608762 | D10: =D9 + C10 -> 652.55866 | E10: {=INDEX(RNG!$C$7:$C$106, (A10-1)*2+2)} -> 0.18 | F10: =-LN(E10)/$B$2 -> 142.89987 | G10: =MAX(D10,H9) -> 704.66063 | H10: =G10 + F10 -> 847.5605 | I10: =G10 - D10 -> 52.10197 | J10: =H10 - D10 -> 195.00184
A11: 5 | B11: {=INDEX(RNG!$C$7:$C$106, (A11-1)*2+1)} -> 0.54 | C11: =-LN(B11)/$B$1 -> 73.740569 | D11: =D10 + C11 -> 726.29923 | E11: {=INDEX(RNG!$C$7:$C$106, (A11-1)*2+2)} -> 0.86 | F11: =-LN(E11)/$B$2 -> 12.568574 | G11: =MAX(D11,H10) -> 847.5605 | H11: =G11 + F11 -> 860.12907 | I11: =G11 - D11 -> 121.26127 | J11: =H11 - D11 -> 133.82984
A12: 6 | B12: {=INDEX(RNG!$C$7:$C$106, (A12-1)*2+1)} -> 0.7 | C12: =-LN(B12)/$B$1 -> 42.684202 | D12: =D11 + C12 -> 768.98343 | E12: {=INDEX(RNG!$C$7:$C$106, (A12-1)*2+2)} -> 0.78 | F12: =-LN(E12)/$B$2 -> 20.705113 | G12: =MAX(D12,H11) -> 860.12907 | H12: =G12 + F12 -> 880.83418 | I12: =G12 - D12 -> 91.145643 | J12: =H12 - D12 -> 111.85076
A13: 7 | B13: {=INDEX(RNG!$C$7:$C$106, (A13-1)*2+1)} -> 0.74 | C13: =-LN(B13)/$B$1 -> 36.034016 | D13: =D12 + C13 -> 805.01744 | E13: {=INDEX(RNG!$C$7:$C$106, (A13-1)*2+2)} -> 0.26 | F13: =-LN(E13)/$B$2 -> 112.25614 | G13: =MAX(D13,H12) -> 880.83418 | H13: =G13 + F13 -> 993.09032 | I13: =G13 - D13 -> 75.81674 | J13: =H13 - D13 -> 188.07288
A14: 8 | B14: {=INDEX(RNG!$C$7:$C$106, (A14-1)*2+1)} -> 0.5 | C14: =-LN(B14)/$B$1 -> 82.950694 | D14: =D13 + C14 -> 887.96814 | E14: {=INDEX(RNG!$C$7:$C$106, (A14-1)*2+2)} -> 0.38 | F14: =-LN(E14)/$B$2 -> 80.632002 | G14: =MAX(D14,H13) -> 993.09032 | H14: =G14 + F14 -> 1073.7223 | I14: =G14 - D14 -> 105.12218 | J14: =H14 - D14 -> 185.75419
A15: 9 | B15: {=INDEX(RNG!$C$7:$C$106, (A15-1)*2+1)} -> 0.94 | C15: =-LN(B15)/$B$1 -> 7.4047876 | D15: =D14 + C15 -> 895.37292 | E15: {=INDEX(RNG!$C$7:$C$106, (A15-1)*2+2)} -> 0.66 | F15: =-LN(E15)/$B$2 -> 34.626287 | G15: =MAX(D15,H14) -> 1073.7223 | H15: =G15 + F15 -> 1108.3486 | I15: =G15 - D15 -> 178.3494 | J15: =H15 - D15 -> 212.97569
A16: 10 | B16: {=INDEX(RNG!$C$7:$C$106, (A16-1)*2+1)} -> 0.3 | C16: =-LN(B16)/$B$1 -> 144.0825 | D16: =D15 + C16 -> 1039.4554 | E16: {=INDEX(RNG!$C$7:$C$106, (A16-1)*2+2)} -> 0.98 | F16: =-LN(E16)/$B$2 -> 1.6835589 | G16: =MAX(D16,H15) -> 1108.3486 | H16: =G16 + F16 -> 1110.0322 | I16: =G16 - D16 -> 68.893185 | J16: =H16 - D16 -> 70.576744
A17: 11 | B17: {=INDEX(RNG!$C$7:$C$106, (A17-1)*2+1)} -> 0.14 | C17: =-LN(B17)/$B$1 -> 235.28975 | D17: =D16 + C17 -> 1274.7452 | E17: {=INDEX(RNG!$C$7:$C$106, (A17-1)*2+2)} -> 0.06 | F17: =-LN(E17)/$B$2 -> 234.45089 | G17: =MAX(D17,H16) -> 1274.7452 | H17: =G17 + F17 -> 1509.1961 | I17: =G17 - D17 -> 0 | J17: =H17 - D17 -> 234.45089
A18: 12 | B18: {=INDEX(RNG!$C$7:$C$106, (A18-1)*2+1)} -> 0.1 | C18: =-LN(B18)/$B$1 -> 275.55624 | D18: =D17 + C18 -> 1550.3014 | E18: {=INDEX(RNG!$C$7:$C$106, (A18-1)*2+2)} -> 0.58 | F18: =-LN(E18)/$B$2 -> 45.393931 | G18: =MAX(D18,H17) -> 1550.3014 | H18: =G18 + F18 -> 1595.6953 | I18: =G18 - D18 -> 0 | J18: =H18 - D18 -> 45.393931
A19: 13 | B19: {=INDEX(RNG!$C$7:$C$106, (A19-1)*2+1)} -> 0.34 | C19: =-LN(B19)/$B$1 -> 129.10391 | D19: =D18 + C19 -> 1679.4053 | E19: {=INDEX(RNG!$C$7:$C$106, (A19-1)*2+2)} -> 0.46 | F19: =-LN(E19)/$B$2 -> 64.710732 | G19: =MAX(D19,H18) -> 1679.4053 | H19: =G19 + F19 -> 1744.1161 | I19: =G19 - D19 -> 0 | J19: =H19 - D19 -> 64.710732
... A31: 25 | B31: {=INDEX(RNG!$C$7:$C$106, (A31-1)*2+1)} -> 0.54 | C31: =-LN(B31)/$B$1 -> 73.740569 | D31: =D30 + C31 -> 2805.2101 | E31: {=INDEX(RNG!$C$7:$C$106, (A31-1)*2+2)} -> 0.86 | F31: =-LN(E31)/$B$2 -> 12.568574 | G31: =MAX(D31,H30) -> 2926.4713 | H31: =G31 + F31 -> 2939.0399 | I31: =G31 - D31 -> 121.26127 | J31: =H31 - D31 -> 133.82984
